torncoder/__init__.py
torncoder/cli/__init__.py
torncoder/cli/file_cache_server.py
torncoder/file_util/__init__.py
torncoder/file_util/_aiofile.py
torncoder/file_util/_core.py
torncoder/file_util/_parser.py
torncoder/file_util/_threaded.py
torncoder/handlers.py
torncoder/subprocess_util.py
torncoder/utils.py
torncoder-0.3.0.dist-info/entry_points.txt
torncoder-0.3.0.dist-info/LICENSE
torncoder-0.3.0.dist-info/WHEEL
torncoder-0.3.0.dist-info/METADATA
torncoder-0.3.0.dist-info/RECORD
